str_analysis/__init__.py
str_analysis/add_adjacent_loci_to_expansion_hunter_catalog.py
str_analysis/add_adjacent_loci_to_expansion_hunter_catalog__manual_unittest.py
str_analysis/add_offtarget_regions.py
str_analysis/annotate_EHdn_locus_outliers.py
str_analysis/annotate_and_filter_str_catalog.py
str_analysis/call_non_ref_motifs.py
str_analysis/check_combined_non_ref_pathogenic_motifs.py
str_analysis/check_combined_results_tsv_for_genome_wide_repeats.py
str_analysis/check_combined_results_tsv_for_pathogenic_repeats.py
str_analysis/check_trios_for_mendelian_violations.py
str_analysis/check_trios_for_mendelian_violations_tests.py
str_analysis/combine_json_to_tsv.py
str_analysis/combine_str_json_to_tsv.py
str_analysis/combine_str_json_to_tsv_tests.py
str_analysis/compute_catalog_stats.py
str_analysis/convert_annotated_EHdn_locus_outliers_to_expansion_hunter_catalog.py
str_analysis/convert_bed_to_expansion_hunter_variant_catalog.py
str_analysis/convert_dat_to_bed.py
str_analysis/convert_expansion_hunter_denovo_locus_tsv_to_bed.py
str_analysis/convert_expansion_hunter_variant_catalog_to_gangstr_spec.py
str_analysis/convert_expansion_hunter_variant_catalog_to_hipstr_format.py
str_analysis/convert_expansion_hunter_variant_catalog_to_longtr_format.py
str_analysis/convert_expansion_hunter_variant_catalog_to_trgt_catalog.py
str_analysis/convert_gangstr_spec_to_expansion_hunter_variant_catalog.py
str_analysis/convert_gangstr_vcf_to_expansion_hunter_json.py
str_analysis/convert_hipstr_vcf_to_expansion_hunter_json.py
str_analysis/convert_strling_calls_to_expansion_hunter_json.py
str_analysis/convert_trgt_vcf_to_expansion_hunter_json.py
str_analysis/copy_EH_vcf_fields_to_json.py
str_analysis/filter_vcf_to_STR_variants.py
str_analysis/filter_vcf_to_STR_variants_tests.py
str_analysis/generate_gnomad_json.py
str_analysis/generate_gnomad_json_tests.py
str_analysis/generate_gnomad_v2_json.py
str_analysis/gnomad_sample_qc.py
str_analysis/make_bamlet.py
str_analysis-1.2.10.dist-info/LICENSE
str_analysis-1.2.10.dist-info/METADATA
str_analysis-1.2.10.dist-info/WHEEL
str_analysis-1.2.10.dist-info/entry_points.txt
str_analysis-1.2.10.dist-info/top_level.txt
str_analysis-1.2.10.dist-info/RECORD
