Metadata-Version: 2.1
Name: str-analysis
Version: 1.2.10
Summary: Utilities for analyzing short tandem repeats (STRs)
Home-page: https://github.com/broadinstitute/str-analysis
License: MIT
Classifier: Development Status :: 4 - Beta
Classifier: Intended Audience :: Developers
Classifier: License :: OSI Approved :: MIT License
Classifier: Natural Language :: English
Classifier: Programming Language :: Python :: 3
Classifier: Programming Language :: Python :: 3.7
Classifier: Programming Language :: Python :: 3.8
Classifier: Programming Language :: Python :: 3.9
Classifier: Programming Language :: Python :: Implementation :: CPython
Classifier: Programming Language :: Python :: Implementation :: PyPy
Requires-Python: >=3.7
License-File: LICENSE
Requires-Dist: google-cloud-storage >=2.14.0
Requires-Dist: hail >=0.2.115
Requires-Dist: ijson >=3.2.2
Requires-Dist: intervaltree >=3.1.0
Requires-Dist: numpy >=1.20.3
Requires-Dist: pandas >=1.1.4
Requires-Dist: pyfaidx >=0.6.4
Requires-Dist: pyBigWig >=0.3.22
Requires-Dist: pysam >=0.16.0.1
Requires-Dist: requests >=2.25.1
Requires-Dist: simplejson >=3.19.2
Requires-Dist: tqdm >=4.62.3
